README.rst
setup.py
django_weed.egg-info/PKG-INFO
django_weed.egg-info/SOURCES.txt
django_weed.egg-info/dependency_links.txt
django_weed.egg-info/requires.txt
django_weed.egg-info/top_level.txt
djweed/__init__.py
djweed/db_fields.py
djweed/storage.py
djweed/urls.py
djweed/version.py
djweed/views.py