Metadata-Version: 1.0
Name: django-weed
Version: 0.1.2
Summary: Weed-FS integration into Django as a storage
Home-page: https://github.com/ProstoKSI/django-weed
Author: Vlad Frolov
Author-email: frolvlad@gmail.com
License: MIT
Platform: UNKNOWN
